CHANGES.rst
CONTRIBUTORS.rst
MANIFEST.in
README.rst
VERSION
VERSION_SUFFIX
setup.cfg
setup.py
docs/LICENSE.GPL
docs/LICENSE.rst
src/visaplan/__init__.py
src/visaplan.zope.reldb.egg-info/PKG-INFO
src/visaplan.zope.reldb.egg-info/SOURCES.txt
src/visaplan.zope.reldb.egg-info/dependency_links.txt
src/visaplan.zope.reldb.egg-info/entry_points.txt
src/visaplan.zope.reldb.egg-info/namespace_packages.txt
src/visaplan.zope.reldb.egg-info/not-zip-safe
src/visaplan.zope.reldb.egg-info/requires.txt
src/visaplan.zope.reldb.egg-info/top_level.txt
src/visaplan/zope/__init__.py
src/visaplan/zope/reldb/__init__.py
src/visaplan/zope/reldb/configure.zcml
src/visaplan/zope/reldb/engine.py
src/visaplan/zope/reldb/legacy.py
src/visaplan/zope/reldb/register.py
src/visaplan/zope/reldb/sql.py