Metadata-Version: 2.1
Name: visaplan.zope.reldb
Version: 1.0.0.dev2
Summary: Configure a Data source name for Zope
Home-page: UNKNOWN
Author: Tobias Herp
Author-email: tobias.herp@visaplan.com
License: GPL version 2
Project-URL: Source, https://github.com/visaplan/zope.reldb
Project-URL: Documentation, https://pypi.org/project/visaplan.zope.reldb
Project-URL: Tracker, https://github.com/visaplan/zope.reldb/issues
Platform: UNKNOWN
Classifier: Environment :: Web Environment
Classifier: Framework :: Plone
Classifier: Framework :: Plone :: 4.3
Classifier: Framework :: Plone :: 5.0
Classifier: Framework :: Plone :: 5.1
Classifier: Framework :: Plone :: 5.2
Classifier: Framework :: Zope
Classifier: Framework :: Zope2
Classifier: Framework :: Zope3
Classifier: Framework :: Zope :: 2
Classifier: Framework :: Zope :: 3
Classifier: Framework :: Zope :: 4
Classifier: Programming Language :: Python
Classifier: Programming Language :: Python :: 2.7
Classifier: Programming Language :: Python :: 3
Classifier: Intended Audience :: Developers
Classifier: Operating System :: OS Independent
Classifier: License :: OSI Approved :: GNU General Public License v2 (GPLv2)
